document_ingesting/__init__.py
document_ingesting/__main__.py
document_ingesting/azure_helper/container_manager.py
document_ingesting/azure_helper/doc_intelligence_lite.py
document_ingesting/azure_helper/doc_intelligence_manager.py
document_ingesting/azure_helper/resource_manager.py
document_ingesting/azure_helper/table_manager.py
document_ingesting/doc_intelligence_parser.py
document_ingesting/doc_split.py
document_ingesting/file_strategy.py
document_ingesting/list_file_strategy.py
document_ingesting/main.py
document_ingesting/openia/embeddings.py
document_ingesting/openia/openai_model.py
document_ingesting/openia/vision.py
document_ingesting/openia/visiontest.prompty
document_ingesting/pdf_merger.py
document_ingesting/search_manager.py
document_ingesting/strategy.py
document_ingesting/text_parser.py
document_ingesting/text_splitter.py
document_ingesting/utils_files.py
document_ingesting-0.1.0.dist-info/METADATA
document_ingesting-0.1.0.dist-info/WHEEL
document_ingesting-0.1.0.dist-info/entry_points.txt
document_ingesting-0.1.0.dist-info/RECORD
