Metadata-Version: 2.1
Name: document-ingesting
Version: 0.1.0
Summary: 
Author: Enrique Botia
Author-email: ebotia@pa.uc3m.es
Requires-Python: >=3.12,<4.0
Classifier: Programming Language :: Python :: 3
Classifier: Programming Language :: Python :: 3.12
Requires-Dist: azaux (>=0.2.1,<0.3.0)
Requires-Dist: azure-ai-documentintelligence (==1.0.0b3)
Requires-Dist: azure-core (>=1.30.1,<2.0.0)
Requires-Dist: azure-data-tables (>=12.5.0,<13.0.0)
Requires-Dist: azure-identity (>=1.16.0,<2.0.0)
Requires-Dist: azure-keyvault (>=4.2.0,<5.0.0)
Requires-Dist: azure-search-documents (>=11.4.0,<12.0.0)
Requires-Dist: azure-storage-blob (>=12.19.1,<13.0.0)
Requires-Dist: imagehash (>=4.3.1,<5.0.0)
Requires-Dist: jinja2 (>=3.1.4,<4.0.0)
Requires-Dist: langchain (>=0.1.16,<0.2.0)
Requires-Dist: openai (>=1.17.1,<2.0.0)
Requires-Dist: openai-messages-token-helper (>=0.1.4,<0.2.0)
Requires-Dist: openpyxl (>=3.1.2,<4.0.0)
Requires-Dist: pandas (>=2.2.2,<3.0.0)
Requires-Dist: pdf2image (>=1.17.0,<2.0.0)
Requires-Dist: pinecone-client (>=3.2.2,<4.0.0)
Requires-Dist: promptflow (>=1.12.0,<2.0.0)
Requires-Dist: promptflow-tools (>=1.4.0,<2.0.0)
Requires-Dist: pypdf (>=4.2.0,<5.0.0)
Requires-Dist: python-dotenv (>=1.0.1,<2.0.0)
Requires-Dist: tenacity (>=8.2.3,<9.0.0)
Requires-Dist: tiktoken (>=0.7.0,<0.8.0)
Requires-Dist: typer[all] (>=0.12.3,<0.13.0)
